Metadata-Version: 2.1
Name: ricktheroll
Version: 0.0.13
Summary: A package that rick rolls people
Home-page: UNKNOWN
Author: Anas (Anas Kattan)
Author-email: <anas@hacktype.tk>
License: UNKNOWN
Keywords: python,rick,roll,rickastley,anas,lol
Platform: UNKNOWN
Classifier: Development Status :: 1 - Planning
Classifier: Intended Audience :: Developers
Classifier: Programming Language :: Python :: 3
Classifier: Operating System :: Unix
Classifier: Operating System :: MacOS :: MacOS X
Classifier: Operating System :: Microsoft :: Windows
